ecotrust_api
