Metadata-Version: 2.1
Name: EcotrustAPI
Version: 1.2.0
Summary: Biblioteca para interação com API do EcotrustET
Home-page: UNKNOWN
Author: EcoIT - Dev Team
Author-email: pablo.viana@ecoit.com.br
License: UNKNOWN
Platform: UNKNOWN
Requires-Python: >=3.9
